skelly_viewer/__init__.py
skelly_viewer/__main__.py
skelly_viewer/test_test.py
skelly_viewer/config/__init__.py
skelly_viewer/config/default_paths.py
skelly_viewer/config/folder_and_file_names.py
skelly_viewer/config/init.py
skelly_viewer/config/logging_configuration.py
skelly_viewer/experimental/checkable_combo_box.py
skelly_viewer/experimental/plotly/plotly_gpt_anim_working1.py
skelly_viewer/gui/__init__.py
skelly_viewer/gui/qt/__init__.py
skelly_viewer/gui/qt/skelly_viewer_widget.py
skelly_viewer/gui/qt/skellyview_main_window.py
skelly_viewer/gui/qt/widgets/__init__.py
skelly_viewer/gui/qt/widgets/init.py
skelly_viewer/gui/qt/widgets/multi_video_display.py
skelly_viewer/gui/qt/widgets/skeleton_view_widget.py
skelly_viewer/gui/qt/widgets/slider_widget.py
skelly_viewer/gui/qt/widgets/time_series_widgets/__init__.py
skelly_viewer/gui/qt/widgets/time_series_widgets/trajectory_view_widget.py
skelly_viewer/gui/qt/widgets/time_series_widgets/sub_widgets/__init__.py
skelly_viewer/gui/qt/widgets/time_series_widgets/sub_widgets/marker_selector_widget.py
skelly_viewer/gui/qt/widgets/time_series_widgets/sub_widgets/time_series_viewer_widget.py
skelly_viewer/utilities/__init__.py
skelly_viewer/utilities/freemocap_data_loader.py
skelly_viewer/utilities/get_video_paths.py
skelly_viewer/utilities/load_sample_data.py
skelly_viewer/utilities/mediapipe_skeleton_builder.py
skelly_viewer/utilities/video_handler.py
skelly_viewer-2025.4.1028.dist-info/entry_points.txt
skelly_viewer-2025.4.1028.dist-info/licenses/LICENSE
skelly_viewer-2025.4.1028.dist-info/WHEEL
skelly_viewer-2025.4.1028.dist-info/METADATA
skelly_viewer-2025.4.1028.dist-info/RECORD
