Metadata-Version: 2.4
Name: skelly_viewer
Version: 2025.4.1028
Summary: View a skelly
Keywords: basic,template,python,repository
Author-email: Skelly FreeMoCap <info@freemocap.org>
Requires-Python: >=3.9,<3.13
Classifier: License :: OSI Approved :: GNU Affero General Public License v3 or later (AGPLv3+)
Classifier: Programming Language :: Python
Classifier: Programming Language :: Python :: 3
License-File: LICENSE
Requires-Dist: pytest
Requires-Dist: numpy==1.26.2
Requires-Dist: rich==13.7.0
Requires-Dist: PySide6==6.6.*
Requires-Dist: opencv-contrib-python==4.8.*
Requires-Dist: pandas==2.1.*
Requires-Dist: matplotlib==3.8.2
Requires-Dist: black ; extra == "dev"
Requires-Dist: bumpver ; extra == "dev"
Requires-Dist: isort ; extra == "dev"
Requires-Dist: pip-tools ; extra == "dev"
Requires-Dist: pytest ; extra == "dev"
Provides-Extra: dev
